cpc.geogrids-0.2.4-py3.6-nspkg.pth
cpc/geogrids/__init__.py
cpc/geogrids/definition.py
cpc/geogrids/exceptions.py
cpc/geogrids/manipulation.py
cpc/geogrids/merging.py
cpc/geogrids/data/station-list-tmean.csv
cpc.geogrids-0.2.4.dist-info/METADATA
cpc.geogrids-0.2.4.dist-info/RECORD
cpc.geogrids-0.2.4.dist-info/WHEEL
cpc.geogrids-0.2.4.dist-info/namespace_packages.txt
cpc.geogrids-0.2.4.dist-info/top_level.txt
