Metadata-Version: 2.1
Name: cpc.geogrids
Version: 0.2.4
Summary: CPC geospatial grids (grid definitions, interpolation, etc.)
Home-page: https://github.com/noaa-nws-cpc/cpc.geogrids
Author: Mike Charles
Author-email: mike.charles@noaa.gov
License: CC
Platform: UNKNOWN
Classifier: Development Status :: 1 - Planning
Classifier: Environment :: Console
Classifier: Intended Audience :: Science/Research
Classifier: Programming Language :: Python
Classifier: Programming Language :: Python :: 3
Classifier: Operating System :: OS Independent
Classifier: Topic :: Scientific/Engineering :: Atmospheric Science
Classifier: License :: CC0 1.0 Universal (CC0 1.0) Public Domain Dedication
Requires-Dist: scipy
Requires-Dist: cpc.stats
